nr/__init__.py
nr/preconditions/__init__.py
nr/preconditions/py.typed
nr.preconditions-0.0.4.dist-info/LICENSE.txt
nr.preconditions-0.0.4.dist-info/METADATA
nr.preconditions-0.0.4.dist-info/WHEEL
nr.preconditions-0.0.4.dist-info/top_level.txt
nr.preconditions-0.0.4.dist-info/RECORD
