Metadata-Version: 2.1
Name: nr.preconditions
Version: 0.0.4
Summary: Provides simple functions to assert the state of your program.
Home-page: https://git.niklasrosenstein.com/NiklasRosenstein/nr
Author: Niklas Rosenstein
Author-email: nrosenstein@palantir.com
License: MIT
Platform: UNKNOWN
Requires-Python: >=3.5.0,<4.0.0
